recreatedb/__init__.py
recreatedb/__version__.py
recreatedb/cli.py
recreatedb/core.py
recreatedb/config/.recreatedb
recreatedb/config/__init__.py
recreatedb-2018.5.1.dist-info/METADATA
recreatedb-2018.5.1.dist-info/RECORD
recreatedb-2018.5.1.dist-info/WHEEL
recreatedb-2018.5.1.dist-info/entry_points.txt
recreatedb-2018.5.1.dist-info/top_level.txt
