Metadata-Version: 2.1
Name: recreatedb
Version: 2018.5.1
Summary: UNKNOWN
Home-page: https://github.com/modernproject/recreatedb
Author: Dylan Stein
Author-email: djstein@ncsu.edu
License: UNKNOWN
Platform: UNKNOWN
Classifier: Programming Language :: Python
Classifier: Programming Language :: Python :: 3.6
Classifier: Programming Language :: Python :: Implementation :: CPython
Classifier: Programming Language :: Python :: Implementation :: PyPy
Requires-Dist: click
Requires-Dist: requests
